opencv_mcp_server/__init__.py
opencv_mcp_server/computer_vision.py
opencv_mcp_server/image_basics.py
opencv_mcp_server/image_processing.py
opencv_mcp_server/main.py
opencv_mcp_server/utils.py
opencv_mcp_server/video_processing.py
iflow_mcp_opencv_mcp_server-0.1.4.dist-info/METADATA
iflow_mcp_opencv_mcp_server-0.1.4.dist-info/WHEEL
iflow_mcp_opencv_mcp_server-0.1.4.dist-info/entry_points.txt
iflow_mcp_opencv_mcp_server-0.1.4.dist-info/licenses/LICENSE
iflow_mcp_opencv_mcp_server-0.1.4.dist-info/RECORD
