Metadata-Version: 2.4
Name: iflow-mcp_opencv-mcp-server
Version: 0.1.4
Summary: MCP server providing OpenCV computer vision capabilities
Project-URL: Homepage, https://github.com/gongrzhe/opencv-mcp-server
Project-URL: Bug Tracker, https://github.com/gongrzhe/opencv-mcp-server/issues
Author-email: GongRzhe <gongrzhe@gmail.com>
License-File: LICENSE
Classifier: License :: OSI Approved :: MIT License
Classifier: Operating System :: OS Independent
Classifier: Programming Language :: Python :: 3
Requires-Python: >=3.11
Requires-Dist: mcp>=1.6.0
Requires-Dist: numpy>=2.2.4
Requires-Dist: opencv-contrib-python>=4.11.0.86
